{
  "project_info": {
    "project_number": "906062760061",
    "project_id": "traveldot-4d22f",
    "storage_bucket": "traveldot-4d22f.firebasestorage.app"
  },
  "client": [
    {
      "client_info": {
        "mobilesdk_app_id": "1:906062760061:android:541fa4d56dbf3c1aeb4914",
        "android_client_info": {
          "package_name": "com.gitpush.visitgrid"
        }
      },
      "oauth_client": [],
      "api_key": [
        {
          "current_key": "AIzaSyB5NpeY1LrjLRJyEDLrMT_kCB0D_L7HaGw"
        }
      ],
      "services": {
        "appinvite_service": {
          "other_platform_oauth_client": []
        }
      }
    }
  ],
  "configuration_version": "1"
}